{"name":"特效","postlist":[{"author":"Irony","title":"PyQt5仿网页图片鼠标移动特效","slug":"likehtmleffect","date":"2018-10-23 17:57:03","updated":"2019-10-21T15:01:38.463Z","comments":null,"path":"api/articles/likehtmleffect.json","excerpt":"em，就是类似于那种游戏官网首页的图片，鼠标放上去后来回移动，图片的前景和背景错位移动。<br>","keywords":null,"cover":"images/ImageSlipped_thumb.jpg","categories":[{"name":"例子","path":"api/categories/例子.json"}],"tags":[{"name":"PyQt","path":"api/tags/PyQt.json"},{"name":"特效","path":"api/tags/特效.json"}]},{"author":"Irony","title":"PyQt5仿网页鼠标移动点阵特效","slug":"rlatticeeffect","date":"2018-10-29 16:49:10","updated":"2019-10-21T15:01:38.463Z","comments":null,"path":"api/articles/rlatticeeffect.json","excerpt":"Orz，前段时间有个zz需求，就是要做一个类似网页上很多个多点连线、鼠标移动跟随的那种炫酷特效，然后花了点时间在网上找了js做的，刚开始打算是嵌入QWebView来显示网页，后来研究了下js的算法代码，遂改用QWidget的paintEvent直接绘制。<br>","keywords":null,"cover":"images/RlatticeEffect_thumb.jpg","categories":[{"name":"例子","path":"api/categories/例子.json"}],"tags":[{"name":"PyQt","path":"api/tags/PyQt.json"},{"name":"动画","path":"api/tags/动画.json"},{"name":"特效","path":"api/tags/特效.json"}]}]}